{
    "name": "ප්‍රේම්නාත් සී.  දොලවත්ත",
    "party": "ශ්‍රී ලංකා පොදුජන පෙරමුණ,",
    "district": "කොළඹ",
    "contact_information": {
        "phone": "718204673",
        "email": "දක්වා නැත"
    },
    "birthday": "1981-11-17",
    "gender": "පුරුෂ",
    "position": {
        "type": "පාර්ලිමේන්තු මන්ත්‍රී",
        "subject": "නැත"
    },
    "biography": "ප්‍රේම්නාත් සී.  දොලවත්ත නැත පාර්ලිමේන්තු මන්ත්‍රී ය. උපන්දිනය 1981-11-17 ය. දුරකථන අංකය සහ විද්‍යුත් තැපෑල පිළිවෙලින් 718204673 දක්වා නැත වේ. කොළඹ දිස්ත්‍රික්කයෙන් ශ්‍රී ලංකා පොදුජන පෙරමුණ,නියෝජනය කරයි."
}