{
    "name": "ප්‍රේමලාල්  ජයසේකර",
    "party": "ශ්‍රී ලංකා පොදුජන පෙරමුණ,",
    "district": "රත්නපුර",
    "contact_information": {
        "phone": "452279173",
        "email": "දක්වා නැත"
    },
    "birthday": "1974-08-05",
    "gender": "පුරුෂ",
    "position": {
        "type": "පාර්ලිමේන්තු මන්ත්‍රී",
        "subject": "නැත"
    },
    "biography": "ප්‍රේමලාල්  ජයසේකර නැත පාර්ලිමේන්තු මන්ත්‍රී ය. උපන්දිනය 1974-08-05 ය. දුරකථන අංකය සහ විද්‍යුත් තැපෑල පිළිවෙලින් 452279173 දක්වා නැත වේ. රත්නපුර දිස්ත්‍රික්කයෙන් ශ්‍රී ලංකා පොදුජන පෙරමුණ,නියෝජනය කරයි."
}