{
    "name": "එස්.එම්  චන්ද්‍රසේන",
    "party": "ශ්‍රී ලංකා පොදුජන පෙරමුණ,",
    "district": "අනුරාධපුර",
    "contact_information": {
        "phone": "252224904",
        "email": "දක්වා නැත"
    },
    "birthday": "1955-03-05",
    "gender": "පුරුෂ",
    "position": {
        "type": "අමාත්‍ය",
        "subject": "ඉඩම්"
    },
    "biography": "එස්.එම්  චන්ද්‍රසේන ඉඩම් අමාත්‍ය ය. උපන්දිනය 1955-03-05 ය. දුරකථන අංකය සහ විද්‍යුත් තැපෑල පිළිවෙලින් 252224904 දක්වා නැත වේ. අනුරාධපුර දිස්ත්‍රික්කයෙන් ශ්‍රී ලංකා පොදුජන පෙරමුණ,නියෝජනය කරයි."
}